[
 {
  "CEDPMADOGBL": 2011850259,
  "CNCDCMNDHMB": 429903631,
  "id": 1,
  "NPDNLJEFGEH": [
   2,
   3
  ],
  "iconName": "UI_RoleCombat_Build_Stream",
  "PIIHOMPNJFF": [
   "5"
  ]
 },
 {
  "CEDPMADOGBL": 3365688211,
  "CNCDCMNDHMB": 3445302079,
  "id": 2,
  "NPDNLJEFGEH": [
   3,
   4
  ],
  "iconName": "UI_RoleCombat_Build_Overgrow",
  "PIIHOMPNJFF": [
   "100"
  ]
 },
 {
  "CEDPMADOGBL": 2171091931,
  "CNCDCMNDHMB": 3159915679,
  "id": 3,
  "NPDNLJEFGEH": [
   2,
   4
  ],
  "iconName": "UI_RoleCombat_Build_Burning",
  "PIIHOMPNJFF": [
   "50"
  ]
 },
 {
  "CEDPMADOGBL": 1826754691,
  "CNCDCMNDHMB": 2584434767,
  "id": 4,
  "NPDNLJEFGEH": [
   2,
   8
  ],
  "iconName": "UI_RoleCombat_Build_CrystallizeFire",
  "PIIHOMPNJFF": [
   "10"
  ]
 },
 {
  "CEDPMADOGBL": 3821726219,
  "CNCDCMNDHMB": 1889877431,
  "id": 5,
  "NPDNLJEFGEH": [
   5,
   8
  ],
  "iconName": "UI_RoleCombat_Build_CrystallizeElectric",
  "PIIHOMPNJFF": [
   "10"
  ]
 },
 {
  "CEDPMADOGBL": 1336059803,
  "CNCDCMNDHMB": 667048663,
  "id": 6,
  "NPDNLJEFGEH": [
   2,
   5
  ],
  "iconName": "UI_RoleCombat_Build_Explode",
  "PIIHOMPNJFF": [
   "1.5"
  ]
 },
 {
  "CEDPMADOGBL": 511820787,
  "CNCDCMNDHMB": 1703916911,
  "id": 7,
  "NPDNLJEFGEH": [
   5,
   4
  ],
  "iconName": "UI_RoleCombat_Build_Overdose"
 },
 {
  "CEDPMADOGBL": 544655123,
  "CNCDCMNDHMB": 2950042823,
  "id": 8,
  "NPDNLJEFGEH": [
   2,
   5
  ],
  "iconName": "UI_RoleCombat_Build_Explode",
  "PIIHOMPNJFF": [
   "1.5"
  ]
 },
 {
  "CEDPMADOGBL": 667174523,
  "CNCDCMNDHMB": 2923179239,
  "id": 9,
  "NPDNLJEFGEH": [
   3,
   7
  ],
  "iconName": "UI_RoleCombat_Build_SwirlWater",
  "PIIHOMPNJFF": [
   "20",
   "2"
  ]
 },
 {
  "CEDPMADOGBL": 3522708539,
  "CNCDCMNDHMB": 3900751551,
  "id": 10,
  "NPDNLJEFGEH": [
   5,
   7
  ],
  "iconName": "UI_RoleCombat_Build_SwirlElectric",
  "PIIHOMPNJFF": [
   "20",
   "0.5"
  ]
 },
 {
  "CEDPMADOGBL": 1864269579,
  "CNCDCMNDHMB": 4107291775,
  "id": 11,
  "NPDNLJEFGEH": [
   3,
   5
  ],
  "iconName": "UI_RoleCombat_Build_ElectroCharged",
  "PIIHOMPNJFF": [
   "50"
  ]
 },
 {
  "CEDPMADOGBL": 1351301355,
  "CNCDCMNDHMB": 3630503743,
  "id": 12,
  "NPDNLJEFGEH": [
   2,
   8
  ],
  "iconName": "UI_RoleCombat_Build_CrystallizeFire",
  "PIIHOMPNJFF": [
   "10"
  ]
 },
 {
  "CEDPMADOGBL": 492870059,
  "CNCDCMNDHMB": 1935928943,
  "id": 13,
  "NPDNLJEFGEH": [
   6,
   8
  ],
  "iconName": "UI_RoleCombat_Build_CrystallizeIce",
  "PIIHOMPNJFF": [
   "10"
  ]
 },
 {
  "CEDPMADOGBL": 2802505779,
  "CNCDCMNDHMB": 270959087,
  "id": 14,
  "NPDNLJEFGEH": [
   2,
   6
  ],
  "iconName": "UI_RoleCombat_Build_Melt"
 },
 {
  "CEDPMADOGBL": 708876131,
  "CNCDCMNDHMB": 1026504359,
  "id": 15,
  "NPDNLJEFGEH": [
   2,
   7
  ],
  "iconName": "UI_RoleCombat_Build_SwirlFire",
  "PIIHOMPNJFF": [
   "20",
   "2"
  ]
 },
 {
  "CEDPMADOGBL": 839009547,
  "CNCDCMNDHMB": 2744564799,
  "id": 16,
  "NPDNLJEFGEH": [
   3,
   6
  ],
  "iconName": "UI_RoleCombat_Build_Frozen",
  "PIIHOMPNJFF": [
   "10"
  ]
 },
 {
  "CEDPMADOGBL": 1969585315,
  "CNCDCMNDHMB": 583663335,
  "id": 17,
  "NPDNLJEFGEH": [
   5,
   6
  ],
  "iconName": "UI_RoleCombat_Build_Superconduct",
  "PIIHOMPNJFF": [
   "1",
   "2"
  ]
 },
 {
  "CEDPMADOGBL": 4100002419,
  "CNCDCMNDHMB": 535909335,
  "id": 18,
  "NPDNLJEFGEH": [
   3,
   8
  ],
  "iconName": "UI_RoleCombat_Build_CrystallizeWater",
  "PIIHOMPNJFF": [
   "10"
  ]
 }
]
